flask_pymodm/__init__.py
flask_pymodm/__version__.py
flask_pymodm/connection.py
flask_pymodm/core.py
flask_pymodm/util.py
Flask_Pymodm-0.1.2.dist-info/LICENSE
Flask_Pymodm-0.1.2.dist-info/METADATA
Flask_Pymodm-0.1.2.dist-info/WHEEL
Flask_Pymodm-0.1.2.dist-info/top_level.txt
Flask_Pymodm-0.1.2.dist-info/RECORD
