Metadata-Version: 2.1
Name: Flask-Pymodm
Version: 0.1.2
Summary: Flask-Pymodm is a simple plugin for Pymodm
Home-page: https://github.com/pbuzulan/flask-pymodm
Author: Petru Buzulan, Daniele Dapuzzo
Author-email: buzulan.petru@gmail.com, daniele.dapuzzo92@gmail.com
License: MIT
Project-URL: Documentation, https://pbuzulan.github.io/flask-pymodm/
Project-URL: Code, https://github.com/pbuzulan/flask-pymodm
Project-URL: Issue tracker, https://github.com/pbuzulan/flask-pymodm/issues
Platform: any
Classifier: Environment :: Web Environment
Classifier: Intended Audience :: Developers
Classifier: License :: OSI Approved :: MIT License
Classifier: Operating System :: OS Independent
Classifier: Programming Language :: Python
Classifier: Programming Language :: Python :: 3
Classifier: Programming Language :: Python :: 3.4
Classifier: Programming Language :: Python :: 3.5
Classifier: Programming Language :: Python :: 3.6
Classifier: Programming Language :: Python :: 3.7
Classifier: Topic :: Internet :: WWW/HTTP :: Dynamic Content
Classifier: Topic :: Software Development :: Libraries :: Python Modules
Requires-Dist: Click (>=7.0)
Requires-Dist: Flask (>=1.1.1)
Requires-Dist: itsdangerous (>=1.1.0)
Requires-Dist: Jinja2 (>=2.10.3)
Requires-Dist: MarkupSafe (==1.1.1)
Requires-Dist: pymodm (>=0.4.2)
Requires-Dist: pymongo (>=3.9.0)
Requires-Dist: Werkzeug (>=0.16.0)
